azure_blob_check/__init__.py
azure_blob_check/blob_check.py
azure_blob_check-2.0.dist-info/LICENSE
azure_blob_check-2.0.dist-info/METADATA
azure_blob_check-2.0.dist-info/WHEEL
azure_blob_check-2.0.dist-info/entry_points.txt
azure_blob_check-2.0.dist-info/top_level.txt
azure_blob_check-2.0.dist-info/RECORD
