Metadata-Version: 2.1
Name: azure-blob-check
Version: 2.0
Summary: azure blob filelist check
Home-page: https://github.com/kyungjunleeme/azure_blob_check
Author: Kyung Jun Lee
Author-email: kyungjunlee.me@gmail.com
License: UNKNOWN
Download-URL: https://github.com/kyungjunleeme/azure_blob_check/archive/main.zip
Keywords: azure_blob,blob_list
Platform: UNKNOWN
Classifier: Programming Language :: Python :: 3.6
Classifier: Programming Language :: Python :: 3.7
Classifier: Programming Language :: Python :: 3.8
Requires-Python: >=3.6
Requires-Dist: azure-storage-blob
Requires-Dist: pytz
Requires-Dist: pandas
Requires-Dist: openpyxl
